eng_join.py
eng_join-0.1.0.dist-info/DESCRIPTION.rst
eng_join-0.1.0.dist-info/METADATA
eng_join-0.1.0.dist-info/RECORD
eng_join-0.1.0.dist-info/WHEEL
eng_join-0.1.0.dist-info/metadata.json
eng_join-0.1.0.dist-info/top_level.txt
