Metadata-Version: 2.0
Name: eng-join
Version: 0.1.0
Summary: A simple english joiner.
Home-page: https://github.com/kennethreitz/eng_join
Author: Kenneth Reitz
Author-email: me@kennethreitz.org
License: MIT
Platform: UNKNOWN
